spatialdata_io/__init__.py
spatialdata_io/__main__.py
spatialdata_io/_docs.py
spatialdata_io/_utils.py
spatialdata_io/_constants/__init__.py
spatialdata_io/_constants/_constants.py
spatialdata_io/_constants/_enum.py
spatialdata_io/converters/__init__.py
spatialdata_io/converters/generic_to_zarr.py
spatialdata_io/converters/legacy_anndata.py
spatialdata_io/experimental/__init__.py
spatialdata_io/readers/__init__.py
spatialdata_io/readers/codex.py
spatialdata_io/readers/cosmx.py
spatialdata_io/readers/curio.py
spatialdata_io/readers/dbit.py
spatialdata_io/readers/generic.py
spatialdata_io/readers/iss.py
spatialdata_io/readers/macsima.py
spatialdata_io/readers/mcmicro.py
spatialdata_io/readers/merscope.py
spatialdata_io/readers/seqfish.py
spatialdata_io/readers/steinbock.py
spatialdata_io/readers/stereoseq.py
spatialdata_io/readers/visium.py
spatialdata_io/readers/visium_hd.py
spatialdata_io/readers/xenium.py
spatialdata_io/readers/_utils/__init__.py
spatialdata_io/readers/_utils/_image.py
spatialdata_io/readers/_utils/_read_10x_h5.py
spatialdata_io/readers/_utils/_utils.py
spatialdata_io-0.6.0.dist-info/METADATA
spatialdata_io-0.6.0.dist-info/WHEEL
spatialdata_io-0.6.0.dist-info/licenses/LICENSE
spatialdata_io-0.6.0.dist-info/RECORD
