Metadata-Version: 2.4
Name: spatialdata-io
Version: 0.6.0
Summary: SpatialData IO for common techs
Project-URL: Documentation, https://spatialdata-io.readthedocs.io/
Project-URL: Source, https://github.com/scverse/spatialdata-io
Project-URL: Home-page, https://github.com/scverse/spatialdata-io
Author: scverse
Maintainer-email: scverse <scverse@scverse.scverse>
License: BSD 3-Clause License
License-File: LICENSE
Requires-Python: >=3.11
Requires-Dist: anndata
Requires-Dist: click
Requires-Dist: dask-image
Requires-Dist: h5py
Requires-Dist: imagecodecs
Requires-Dist: joblib
Requires-Dist: numpy
Requires-Dist: ome-types
Requires-Dist: pyarrow
Requires-Dist: readfcs
Requires-Dist: scanpy
Requires-Dist: scikit-image
Requires-Dist: spatialdata>=0.2.6
Requires-Dist: tifffile>=2023.8.12
Requires-Dist: xmltodict
Provides-Extra: dev
Requires-Dist: bump2version; extra == 'dev'
Requires-Dist: pre-commit; extra == 'dev'
Provides-Extra: doc
Requires-Dist: ipython>=8.6.0; extra == 'doc'
Requires-Dist: myst-nb; extra == 'doc'
Requires-Dist: sphinx-autodoc-typehints; extra == 'doc'
Requires-Dist: sphinx-book-theme>=1.0.0; extra == 'doc'
Requires-Dist: sphinx-click; extra == 'doc'
Requires-Dist: sphinx-copybutton; extra == 'doc'
Requires-Dist: sphinx-design; extra == 'doc'
Requires-Dist: sphinx>=4.5; extra == 'doc'
Requires-Dist: sphinxcontrib-bibtex>=1.0.0; extra == 'doc'
Provides-Extra: pre
Requires-Dist: spatialdata>=0.4.0rc0; extra == 'pre'
Provides-Extra: test
Requires-Dist: pyarrow!=22; extra == 'test'
Requires-Dist: pytest; extra == 'test'
Requires-Dist: pytest-cov; extra == 'test'
